{
  "dataset_type": "positive",
  "feature": "functions",
  "category": "async_functions",
  "description": "Asynchronous functions with promises, callbacks, and async patterns",
  "examples": [
    {
      "id": "async-001",
      "intent": "Simple async function",
      "input": {
        "natural_language": "Fetch data asynchronously",
        "context": {
          "scope": "component"
        }
      },
      "expected_output": {
        "quantum_code": "<q:function name=\"fetchUserData\" async=\"true\">\n  <q:param name=\"userId\" type=\"string\" required=\"true\" />\n  <q:invoke name=\"fetchUser\" url=\"https://api.example.com/users/{userId}\" method=\"GET\" result=\"userData\" />\n  <q:return value=\"{userData}\" />\n</q:function>",
        "runtime_behavior": "Returns promise that resolves with user data"
      },
      "tags": ["async", "fetch", "promise"]
    },
    {
      "id": "async-005",
      "intent": "Async with timeout",
      "input": {
        "natural_language": "Fetch with 5 second timeout",
        "context": {
          "scope": "component"
        }
      },
      "expected_output": {
        "quantum_code": "<q:function name=\"fetchWithTimeout\" async=\"true\" timeout=\"5000\">\n  <q:param name=\"url\" type=\"string\" required=\"true\" />\n  <q:invoke name=\"fetchUrl\" url=\"{url}\" method=\"GET\" result=\"responseData\" />\n  <q:return value=\"{responseData}\" />\n</q:function>",
        "runtime_behavior": "Aborts request after 5 seconds if not completed"
      },
      "tags": ["async", "timeout", "performance"]
    }
  ]
}
